astra_rl/__init__.py
astra_rl/cli/__init__.py
astra_rl/cli/evaluate.py
astra_rl/cli/main.py
astra_rl/cli/train.py
astra_rl-0.0.1.dist-info/licenses/LICENSE
astra_rl-0.0.1.dist-info/METADATA
astra_rl-0.0.1.dist-info/WHEEL
astra_rl-0.0.1.dist-info/entry_points.txt
astra_rl-0.0.1.dist-info/top_level.txt
astra_rl-0.0.1.dist-info/RECORD
